{
  "title": "AI Tools Work. Does Your Engineering Process?",
  "author": "Julien Simon",
  "date": "2026-03-05",
  "description": "Few people in the history of computing have earned the right to be skeptical more than Donald Knuth. If you spent long hours withThe Art of Computer Programming\u2014 the multi-volume work that Dijkstra...",
  "read_time": "38 min read",
  "tags": [
    "AI",
    "Technology"
  ],
  "category": "Industry Perspectives",
  "original_url": "https://www.airealist.ai/p/ai-tools-work-does-your-engineering",
  "image_count": 1
}
