{
  "title": "Objects That Struck the Data Center",
  "author": "Julien Simon",
  "date": "2026-03-02",
  "description": "At 4:30 in the morning Pacific time on March 1, 2026, Amazon Web Services posted an incident report for its ME-CENTRAL-1 region in the United Arab Emirates. The language was remarkable \u2014 not for wh...",
  "read_time": "24 min read",
  "tags": [
    "AI",
    "Technology"
  ],
  "category": "Industry Perspectives",
  "original_url": "https://www.airealist.ai/p/objects-that-struck-the-data-center",
  "image_count": 1
}
